{
  "description": {
    "name": "Nick",
    "title": "Fotógrafo profesional y otras cosas",
    "bio": "Lorem ipsum dolor sit amet, adipiscing elit at sodales etiam. Curabitur mauris purus. Mauris feugiat eget augue rutrum blandit. Phasellus maximus elit mauris, sed lorem finibus eget."
  },
  "socials": [
    { "name": "Instagram", "icon": "InstagramIcon", "link": "#" },
    { "name": "Okru", "icon": "OkruIcon", "link": "#" },
    { "name": "Twitch", "icon": "TwitchIcon", "link": "#" },
    { "name": "Youtube", "icon": "YoutubeIcon", "link": "#" },
    { "name": "TikTok", "icon": "TiktokIcon", "link": "#" },
    { "name": "X (Twitter)", "icon": "TwitterXIcon", "link": "#" }
  ],
  "schedule": {
    "header": [
      "Lunes",
      "Martes",
      "Miércoles",
      "Jueves",
      "Viernes",
      "Sábado",
      "Domingo"
    ],
    "rows": [
      [
        "Título Lunes",
        "Título Martes",
        "Título Miércoles",
        "Título Jueves",
        "Título Viernes",
        "Título Sábado",
        "Título Domingo"
      ],
      [
        "Detalle Lunes",
        "Detalle Martes",
        "Detalle Miércoles",
        "Detalle Jueves",
        "Detalle Viernes",
        "Detalle Sábado",
        "Detalle Domingo"
      ]
    ]
  },
  "animeImages": {
    "img_folderAnime": "/image/img_folderAnime.png",
    "img_battleSong": "/image/img_battleSong.png"
  },
  "links": {
    "battleSong": "https://songbattle.io/"
  }
}
